examples/__init__.py
examples/particle/__init__.py
examples/particle/azure/__init__.py
examples/particle/azure/blob/__init__.py
examples/particle/azure/blob/use_blob_container/__init__.py
examples/particle/azure/blob/use_blob_container/example_blob_container.py
pcf/__init__.py
pcf/cli/__init__.py
pcf/cli/cli.py
pcf/cli/utils.py
pcf/cli/commands/__init__.py
pcf/cli/commands/apply.py
pcf/cli/commands/run.py
pcf/cli/commands/stop.py
pcf/cli/commands/terminate.py
pcf/core/__init__.py
pcf/core/aws_resource.py
pcf/core/azure_resource.py
pcf/core/gcp_resource.py
pcf/core/particle.py
pcf/core/particle_flavor_scanner.py
pcf/core/pcf.py
pcf/core/pcf_exceptions.py
pcf/core/quasiparticle.py
pcf/extended_particles/__init__.py
pcf/extended_particles/aws/__init__.py
pcf/extended_particles/aws/lambda_function/__init__.py
pcf/extended_particles/aws/lambda_function/lambda_python.py
pcf/particle/__init__.py
pcf/particle/aws/__init__.py
pcf/particle/aws/batch/__init__.py
pcf/particle/aws/batch/batch_compute_environment.py
pcf/particle/aws/batch/batch_job_queue.py
pcf/particle/aws/cloudformation/__init__.py
pcf/particle/aws/cloudformation/cloudformation_stack.py
pcf/particle/aws/cloudfront/__init__.py
pcf/particle/aws/cloudfront/cloudfront_distribution.py
pcf/particle/aws/cloudwatch/__init__.py
pcf/particle/aws/cloudwatch/cloudwatch_event.py
pcf/particle/aws/cloudwatch/cloudwatch_log.py
pcf/particle/aws/dynamodb/__init__.py
pcf/particle/aws/dynamodb/dynamodb_table.py
pcf/particle/aws/ec2/__init__.py
pcf/particle/aws/ec2/ebs_volume.py
pcf/particle/aws/ec2/ec2_instance.py
pcf/particle/aws/ec2/alb/__init__.py
pcf/particle/aws/ec2/alb/alb.py
pcf/particle/aws/ec2/autoscaling/__init__.py
pcf/particle/aws/ec2/autoscaling/auto_scaling_group.py
pcf/particle/aws/ec2/autoscaling/launch_configuration.py
pcf/particle/aws/ec2/elb/__init__.py
pcf/particle/aws/ec2/elb/elb.py
pcf/particle/aws/ecr/__init__.py
pcf/particle/aws/ecr/ecr_repository.py
pcf/particle/aws/ecs/__init__.py
pcf-0.4.7.dist-info/LICENSE
pcf-0.4.7.dist-info/METADATA
pcf-0.4.7.dist-info/WHEEL
pcf-0.4.7.dist-info/entry_points.txt
pcf-0.4.7.dist-info/top_level.txt
pcf-0.4.7.dist-info/RECORD
