Metadata-Version: 2.1
Name: pcf
Version: 0.4.7
Summary: pcf
Home-page: https://github.com/capitalone/Particle-Cloud-Framework
Author: anovis,bb1314,davidyum
License: UNKNOWN
Platform: UNKNOWN
Classifier: Programming Language :: Python :: 3.6
Classifier: Programming Language :: Python :: 3.7
Classifier: License :: OSI Approved :: Apache Software License
Classifier: Operating System :: OS Independent
Requires-Dist: azure-storage-common (==1.4.0)
Requires-Dist: azure-storage-blob (==1.5.0)
Requires-Dist: azure-common (==1.1.20)
Requires-Dist: azure-mgmt-compute (==4.6.2)
Requires-Dist: azure-mgmt-resource (==2.1.0)
Requires-Dist: azure-mgmt-network (==2.7.0)
Requires-Dist: azure-mgmt-storage (==3.3.0)
Requires-Dist: azure-cli-core (==2.0.57)
Requires-Dist: boto (==2.48.0)
Requires-Dist: boto3 (==1.9.143)
Requires-Dist: Jinja2 (==2.10.1)
Requires-Dist: google-compute-engine (==2.8.13)
Requires-Dist: google-cloud-storage (==1.15.0)
Requires-Dist: google-api-python-client (==1.7.4)
Requires-Dist: commentjson (==0.7.1)
Requires-Dist: botocore (==1.12.143)
Requires-Dist: deepdiff (==4.0.6)
Requires-Dist: click (==7.0)
Requires-Dist: python-Levenshtein (==0.12.0)
Requires-Dist: pyyaml (==5.1)
